{
  "formatVersion": 1,
  "database": {
    "version": 2,
    "identityHash": "dea0532a7099f0beeed839e1ce60aa10",
    "entities": [
      {
        "tableName": "profile",
        "createSql": "CREATE TABLE IF NOT EXISTS `${TABLE_NAME}` (`id` INTEGER NOT NULL, `gender` TEXT NOT NULL, `ageYears` INTEGER NOT NULL, `heightCm` INTEGER NOT NULL, `weightKg` REAL, `activityLevel` TEXT NOT NULL, `daysPerWeek` INTEGER NOT NULL, `goal` TEXT NOT NULL, `paceKgPerWeek` REAL NOT NULL, `updatedAt` INTEGER NOT NULL, `dirty` INTEGER NOT NULL, PRIMARY KEY(`id`))",
        "fields": [
          {
            "fieldPath": "id",
            "columnName": "id",
            "affinity": "INTEGER",
            "notNull": true
          },
          {
            "fieldPath": "gender",
            "columnName": "gender",
            "affinity": "TEXT",
            "notNull": true
          },
          {
            "fieldPath": "ageYears",
            "columnName": "ageYears",
            "affinity": "INTEGER",
            "notNull": true
          },
          {
            "fieldPath": "heightCm",
            "columnName": "heightCm",
            "affinity": "INTEGER",
            "notNull": true
          },
          {
            "fieldPath": "weightKg",
            "columnName": "weightKg",
            "affinity": "REAL"
          },
          {
            "fieldPath": "activityLevel",
            "columnName": "activityLevel",
            "affinity": "TEXT",
            "notNull": true
          },
          {
            "fieldPath": "daysPerWeek",
            "columnName": "daysPerWeek",
            "affinity": "INTEGER",
            "notNull": true
          },
          {
            "fieldPath": "goal",
            "columnName": "goal",
            "affinity": "TEXT",
            "notNull": true
          },
          {
            "fieldPath": "paceKgPerWeek",
            "columnName": "paceKgPerWeek",
            "affinity": "REAL",
            "notNull": true
          },
          {
            "fieldPath": "updatedAt",
            "columnName": "updatedAt",
            "affinity": "INTEGER",
            "notNull": true
          },
          {
            "fieldPath": "dirty",
            "columnName": "dirty",
            "affinity": "INTEGER",
            "notNull": true
          }
        ],
        "primaryKey": {
          "autoGenerate": false,
          "columnNames": [
            "id"
          ]
        }
      },
      {
        "tableName": "weight_samples",
        "createSql": "CREATE TABLE IF NOT EXISTS `${TABLE_NAME}` (`id` INTEGER PRIMARY KEY AUTOINCREMENT NOT NULL, `dateMs` INTEGER NOT NULL, `weightKg` REAL NOT NULL, `updatedAt` INTEGER NOT NULL, `dirty` INTEGER NOT NULL)",
        "fields": [
          {
            "fieldPath": "id",
            "columnName": "id",
            "affinity": "INTEGER",
            "notNull": true
          },
          {
            "fieldPath": "dateMs",
            "columnName": "dateMs",
            "affinity": "INTEGER",
            "notNull": true
          },
          {
            "fieldPath": "weightKg",
            "columnName": "weightKg",
            "affinity": "REAL",
            "notNull": true
          },
          {
            "fieldPath": "updatedAt",
            "columnName": "updatedAt",
            "affinity": "INTEGER",
            "notNull": true
          },
          {
            "fieldPath": "dirty",
            "columnName": "dirty",
            "affinity": "INTEGER",
            "notNull": true
          }
        ],
        "primaryKey": {
          "autoGenerate": true,
          "columnNames": [
            "id"
          ]
        }
      },
      {
        "tableName": "energy_logs",
        "createSql": "CREATE TABLE IF NOT EXISTS `${TABLE_NAME}` (`id` INTEGER PRIMARY KEY AUTOINCREMENT NOT NULL, `dateMs` INTEGER NOT NULL, `kcalConsumed` INTEGER NOT NULL, `isComplete` INTEGER NOT NULL, `updatedAt` INTEGER NOT NULL, `dirty` INTEGER NOT NULL)",
        "fields": [
          {
            "fieldPath": "id",
            "columnName": "id",
            "affinity": "INTEGER",
            "notNull": true
          },
          {
            "fieldPath": "dateMs",
            "columnName": "dateMs",
            "affinity": "INTEGER",
            "notNull": true
          },
          {
            "fieldPath": "kcalConsumed",
            "columnName": "kcalConsumed",
            "affinity": "INTEGER",
            "notNull": true
          },
          {
            "fieldPath": "isComplete",
            "columnName": "isComplete",
            "affinity": "INTEGER",
            "notNull": true
          },
          {
            "fieldPath": "updatedAt",
            "columnName": "updatedAt",
            "affinity": "INTEGER",
            "notNull": true
          },
          {
            "fieldPath": "dirty",
            "columnName": "dirty",
            "affinity": "INTEGER",
            "notNull": true
          }
        ],
        "primaryKey": {
          "autoGenerate": true,
          "columnNames": [
            "id"
          ]
        }
      },
      {
        "tableName": "ai_memory",
        "createSql": "CREATE TABLE IF NOT EXISTS `${TABLE_NAME}` (`id` INTEGER PRIMARY KEY AUTOINCREMENT NOT NULL, `note` TEXT NOT NULL, `createdAt` INTEGER NOT NULL, `updatedAt` INTEGER NOT NULL, `dirty` INTEGER NOT NULL)",
        "fields": [
          {
            "fieldPath": "id",
            "columnName": "id",
            "affinity": "INTEGER",
            "notNull": true
          },
          {
            "fieldPath": "note",
            "columnName": "note",
            "affinity": "TEXT",
            "notNull": true
          },
          {
            "fieldPath": "createdAt",
            "columnName": "createdAt",
            "affinity": "INTEGER",
            "notNull": true
          },
          {
            "fieldPath": "updatedAt",
            "columnName": "updatedAt",
            "affinity": "INTEGER",
            "notNull": true
          },
          {
            "fieldPath": "dirty",
            "columnName": "dirty",
            "affinity": "INTEGER",
            "notNull": true
          }
        ],
        "primaryKey": {
          "autoGenerate": true,
          "columnNames": [
            "id"
          ]
        }
      }
    ],
    "setupQueries": [
      "CREATE TABLE IF NOT EXISTS room_master_table (id INTEGER PRIMARY KEY,identity_hash TEXT)",
      "INSERT OR REPLACE INTO room_master_table (id,identity_hash) VALUES(42, 'dea0532a7099f0beeed839e1ce60aa10')"
    ]
  }
}